raspi_gpio/GPIO_mock.py
raspi_gpio/__init__.py
raspi_gpio/spidev_mock.py
raspi_gpio-0.1.9.dist-info/LICENSE
raspi_gpio-0.1.9.dist-info/METADATA
raspi_gpio-0.1.9.dist-info/WHEEL
raspi_gpio-0.1.9.dist-info/RECORD
